netbox_aci/__init__.py
netbox_aci/choices.py
netbox_aci/filtersets.py
netbox_aci/navigation.py
netbox_aci/search.py
netbox_aci/template_content.py
netbox_aci/urls.py
netbox_aci/api/__init__.py
netbox_aci/api/serializers.py
netbox_aci/api/urls.py
netbox_aci/api/views.py
netbox_aci/forms/__init__.py
netbox_aci/forms/aaep_form.py
netbox_aci/forms/ap_form.py
netbox_aci/forms/bd_form.py
netbox_aci/forms/contract_filter_entry_form.py
netbox_aci/forms/contract_filter_form.py
netbox_aci/forms/contract_form.py
netbox_aci/forms/contract_subject_form.py
netbox_aci/forms/domain_form.py
netbox_aci/forms/epg_form.py
netbox_aci/forms/esg_form.py
netbox_aci/forms/ipg_form.py
netbox_aci/forms/l3out_form.py
netbox_aci/forms/policies_form.py
netbox_aci/migrations/0001_initial.py
netbox_aci/migrations/0002_policygroup_type_cdp_policygroup_cdp_lldp_and_more.py
netbox_aci/migrations/0003_alter_contractfilter_name_alter_contractfilter_slug_and_more.py
netbox_aci/migrations/__init__.py
netbox_aci/models/__init__.py
netbox_aci/models/aaep_model.py
netbox_aci/models/ap_model.py
netbox_aci/models/bd_model.py
netbox_aci/models/contract_filter_entry_model.py
netbox_aci/models/contract_filter_model.py
netbox_aci/models/contract_model.py
netbox_aci/models/contract_subject_model.py
netbox_aci/models/default_model.py
netbox_aci/models/domain_model.py
netbox_aci/models/epg_model.py
netbox_aci/models/esg_model.py
netbox_aci/models/ipg_model.py
netbox_aci/models/l3out_model.py
netbox_aci/models/policies_model.py
netbox_aci/tables/__init__.py
netbox_aci/tables/aaep_tables.py
netbox_aci/tables/ap_tables.py
netbox_aci/tables/bd_tables.py
netbox_aci/tables/contract_tables.py
netbox_aci/tables/domain_tables.py
netbox_aci/tables/epg_tables.py
netbox_aci/tables/esg_tables.py
netbox_aci/tables/ipg_tables.py
netbox_aci/tables/l3out_tables.py
netbox_aci/tables/policies_tables.py
netbox_aci/templates/netbox_aci/aaep.html
netbox_aci/templates/netbox_aci/aaep_details.html
netbox_aci-0.0.6.dist-info/licenses/LICENSE
netbox_aci-0.0.6.dist-info/METADATA
netbox_aci-0.0.6.dist-info/WHEEL
netbox_aci-0.0.6.dist-info/top_level.txt
netbox_aci-0.0.6.dist-info/RECORD
