Metadata-Version: 2.4
Name: netbox-aci
Version: 0.0.6
Summary: A NetBox plugin to integrate Cisco ACI (Application Centric Infrastructure) with NetBox.
Author: Marc-Aurel Mohr-Lenné
License: 
Project-URL: Homepage, https://github.com/bechtle-bms/netbox-aci
Project-URL: Documentation, https://github.com/bechtle-bms/netbox-aci/blob/main/README.md
Project-URL: Repository, https://github.com/bechtle-bms/netbox-aci
Project-URL: Issues, https://github.com/bechtle-bms/netbox-aci/issues
Classifier: Programming Language :: Python :: 3
Requires-Python: >=3.10.0
License-File: LICENSE
Dynamic: license-file
